lmcmd/__init__.py
lmcmd/main.py
lmcmd/terminal/terminal.py
lmcmd-0.1.2.dist-info/LICENSE
lmcmd-0.1.2.dist-info/METADATA
lmcmd-0.1.2.dist-info/WHEEL
lmcmd-0.1.2.dist-info/entry_points.txt
lmcmd-0.1.2.dist-info/RECORD
