Metadata-Version: 2.1
Name: lmcmd
Version: 0.1.2
Summary: The Fast lmdb Command Client
Author: Jack.Zhang
Author-email: 17284782591@163.com
Requires-Python: >=3.8,<4.0
Classifier: Programming Language :: Python :: 3
Classifier: Programming Language :: Python :: 3.8
Classifier: Programming Language :: Python :: 3.9
Classifier: Programming Language :: Python :: 3.10
Classifier: Programming Language :: Python :: 3.11
Classifier: Programming Language :: Python :: 3.12
Classifier: Programming Language :: Python :: 3.13
Requires-Dist: lmdb (>=1.6.2,<2.0.0)
Requires-Dist: pytest (>=8.3.5,<9.0.0)
